setup.py
Flask_Jigger.egg-info/PKG-INFO
Flask_Jigger.egg-info/SOURCES.txt
Flask_Jigger.egg-info/dependency_links.txt
Flask_Jigger.egg-info/top_level.txt
flask_jigger/__init__.py
flask_jigger/renderers.py
flask_jigger/status.py
flask_jigger/urlrules.py
flask_jigger/views.py
flask_jigger/hateoas/__init__.py
flask_jigger/hateoas/mongo.py
flask_jigger/livedoc/__init__.py
flask_jigger/livedoc/swagger.py
flask_jigger/tests/__init__.py
flask_jigger/tests/test_urlrules.py
flask_jigger/tests/test_views.py
flask_jigger/tests/livedoc/__init__.py
flask_jigger/tests/livedoc/test_swaggerdoc.py
flask_jigger/util/__init__.py
flask_jigger/util/breadcrumbs.py
flask_jigger/util/encoders.py