Metadata-Version: 1.0
Name: Flask-Jigger
Version: 0.0.2
Summary: Web APIs for Flask, unintrusive.
Home-page: https://github.com/robvanmieghem/flask-jigger
Author: Rob Van Mieghem
Author-email: rob@vanmieghemcloud.com
License: UNKNOWN
Download-URL: http://pypi.python.org/pypi/flask-jigger/
Platform: UNKNOWN
Classifier: Development Status :: 2 - Pre-Alpha
Classifier: Environment :: Web Environment
Classifier: Intended Audience :: Developers
Classifier: License :: OSI Approved :: Apache Software License
Classifier: Operating System :: OS Independent
Classifier: Programming Language :: Python
Classifier: Topic :: Internet :: WWW/HTTP
